mozurestsdk/__init__.py
mozurestsdk/apicontext.py
mozurestsdk/apiexception.py
mozurestsdk/config.py
mozurestsdk/headers.py
mozurestsdk/mozuclient.py
mozurestsdk/mozuurl.py
mozurestsdk/urllocation.py
mozurestsdk/util.py
mozurestsdk/version.py
mozurestsdk/commerce/__init__.py
mozurestsdk/commerce/cart.py
mozurestsdk/commerce/channel.py
mozurestsdk/commerce/channelgroup.py
mozurestsdk/commerce/instocknotificationsubscription.py
mozurestsdk/commerce/location.py
mozurestsdk/commerce/order.py
mozurestsdk/commerce/return.py
mozurestsdk/commerce/targetrule.py
mozurestsdk/commerce/wishlist.py
mozurestsdk/commerce/admin/__init__.py
mozurestsdk/commerce/admin/location.py
mozurestsdk/commerce/admin/locationtype.py
mozurestsdk/commerce/carts/__init__.py
mozurestsdk/commerce/carts/applieddiscount.py
mozurestsdk/commerce/carts/cartitem.py
mozurestsdk/commerce/carts/changemessage.py
mozurestsdk/commerce/carts/extendedproperty.py
mozurestsdk/commerce/catalog/__init__.py
mozurestsdk/commerce/catalog/admin/__init__.py
mozurestsdk/commerce/catalog/admin/category.py
mozurestsdk/commerce/catalog/admin/couponset.py
mozurestsdk/commerce/catalog/admin/discount.py
mozurestsdk/commerce/catalog/admin/facet.py
mozurestsdk/commerce/catalog/admin/locationinventory.py
mozurestsdk/commerce/catalog/admin/mastercatalog.py
mozurestsdk/commerce/catalog/admin/pricelist.py
mozurestsdk/commerce/catalog/admin/product.py
mozurestsdk/commerce/catalog/admin/productreservation.py
mozurestsdk/commerce/catalog/admin/publishingscope.py
mozurestsdk/commerce/catalog/admin/search.py
mozurestsdk/commerce/catalog/admin/softallocation.py
mozurestsdk/commerce/catalog/admin/attributedefinition/__init__.py
mozurestsdk/commerce/catalog/admin/attributedefinition/attribute.py
mozurestsdk/commerce/catalog/admin/attributedefinition/producttype.py
mozurestsdk/commerce/catalog/admin/attributedefinition/attributes/__init__.py
mozurestsdk-1.2.0.dist-info/DESCRIPTION.rst
mozurestsdk-1.2.0.dist-info/METADATA
mozurestsdk-1.2.0.dist-info/RECORD
mozurestsdk-1.2.0.dist-info/WHEEL
mozurestsdk-1.2.0.dist-info/metadata.json
mozurestsdk-1.2.0.dist-info/top_level.txt
