Metadata-Version: 2.0
Name: mozurestsdk
Version: 1.2.0
Summary: Mozu Rest SDK.
Home-page: https://github.com/mozu/mozu-python-sdk
Author: Mozu
Author-email: integrations@mozu.com
License: Apache License
Keywords: mozu,rest,sdk
Platform: UNKNOWN
Classifier: Development Status :: 5 - Production/Stable
Classifier: Intended Audience :: Developers
Classifier: Natural Language :: English
Classifier: Operating System :: OS Independent
Classifier: Programming Language :: Python :: 3.4
Classifier: Programming Language :: Python :: Implementation :: PyPy
Classifier: Topic :: Software Development :: Libraries :: Python Modules
Requires-Dist: requests
Requires-Dist: six
Provides-Extra: test
Requires-Dist: coverage; extra == 'test'
